{"type": "FeatureCollection", "features": [{"type": "Feature", "geometry": {"type": "Point", "coordinates": [-61.7696855, 16.1285409]}, "properties": {"id": 1348307563, "camera:mount": "wall", "camera:type": "dome", "man_made": "surveillance", "surveillance": "outdoor", "surveillance:type": "camera", "surveillance:zone": "bank", "data_source": "planet_osm"}}, {"type": "Feature", "geometry": {"type": "Point", "coordinates": [-61.6960832, 16.0267491]}, "properties": {"id": 5697631619, "camera:mount": "pole", "camera:type": "dome", "man_made": "surveillance", "mapillary": "175947430982363", "surveillance": "outdoor", "surveillance:type": "camera", "surveillance:zone": "town", "data_source": "planet_osm"}}, {"type": "Feature", "geometry": {"type": "Point", "coordinates": [-61.6982867, 16.0254014]}, "properties": {"id": 6140506545, "camera:direction": "360", "camera:mount": "pole", "camera:type": "dome", "man_made": "surveillance", "mapillary": "276360627532233", "surveillance": "outdoor", "surveillance:type": "camera", "surveillance:zone": "town", "data_source": "planet_osm"}}, {"type": "Feature", "geometry": {"type": "Point", "coordinates": [-61.2731247, 16.2506102]}, "properties": {"id": 6904883522, "man_made": "surveillance", "surveillance:type": "camera", "data_source": "planet_osm"}}, {"type": "Feature", "geometry": {"type": "Point", "coordinates": [-61.0943156, 14.6201285]}, "properties": {"id": 8359154718, "camera:mount": "street_lamp", "camera:type": "fixed", "man_made": "surveillance", "surveillance": "outdoor", "surveillance:type": "camera", "surveillance:zone": "parking", "survey:date": "2021-01-24", "data_source": "planet_osm"}}, {"type": "Feature", "geometry": {"type": "Point", "coordinates": [-61.094168, 14.6201315]}, "properties": {"id": 8359158618, "camera:mount": "street_lamp", "camera:type": "fixed", "man_made": "surveillance", "surveillance": "outdoor", "surveillance:type": "camera", "surveillance:zone": "parking", "survey:date": "2021-01-24", "data_source": "planet_osm"}}, {"type": "Feature", "geometry": {"type": "Point", "coordinates": [-61.0944439, 14.6201308]}, "properties": {"id": 8359159117, "camera:mount": "street_lamp", "camera:type": "fixed", "man_made": "surveillance", "surveillance": "outdoor", "surveillance:type": "camera", "surveillance:zone": "parking", "survey:date": "2021-01-24", "data_source": "planet_osm"}}, {"type": "Feature", "geometry": {"type": "Point", "coordinates": [-61.0636811, 14.6049027]}, "properties": {"camera:mount": "street_lamp", "camera:type": "dome", "man_made": "surveillance", "surveillance": "public", "surveillance:type": "camera", "surveillance:zone": "traffic"}}, {"type": "Feature", "geometry": {"type": "Point", "coordinates": [-61.3153379, 16.2549602]}, "properties": {"man_made": "surveillance"}}, {"type": "Feature", "geometry": {"type": "Point", "coordinates": [-61.3395564, 16.3299811]}, "properties": {"man_made": "surveillance"}}, {"type": "Feature", "geometry": {"type": "Point", "coordinates": [-61.3098697, 16.2567578]}, "properties": {"man_made": "surveillance"}}, {"type": "Feature", "geometry": {"type": "Point", "coordinates": [-61.2877738, 16.2858983]}, "properties": {"man_made": "surveillance"}}, {"type": "Feature", "geometry": {"type": "Point", "coordinates": [-61.3155233, 16.2549036]}, "properties": {"man_made": "surveillance"}}, {"type": "Feature", "geometry": {"type": "Point", "coordinates": [-61.2892727, 16.2907046]}, "properties": {"man_made": "surveillance"}}, {"type": "Feature", "geometry": {"type": "Point", "coordinates": [-61.3395466, 16.329995]}, "properties": {"man_made": "surveillance"}}, {"type": "Feature", "geometry": {"type": "Point", "coordinates": [-61.4688508, 16.4103337]}, "properties": {"man_made": "surveillance"}}, {"type": "Feature", "geometry": {"type": "Point", "coordinates": [-61.5055187, 16.2853127]}, "properties": {"man_made": "surveillance"}}, {"type": "Feature", "geometry": {"type": "Point", "coordinates": [-61.5097915, 16.2744285]}, "properties": {"man_made": "surveillance"}}, {"type": "Feature", "geometry": {"type": "Point", "coordinates": [-61.4557119, 16.3510825]}, "properties": {"man_made": "surveillance"}}, {"type": "Feature", "geometry": {"type": "Point", "coordinates": [-61.3389531, 16.3314731]}, "properties": {"man_made": "surveillance", "surveillance:type": "camera"}}, {"type": "Feature", "geometry": {"type": "Point", "coordinates": [-61.4857897, 16.3787296]}, "properties": {"man_made": "surveillance", "surveillance:type": "camera"}}, {"type": "Feature", "geometry": {"type": "Point", "coordinates": [-61.4607008, 16.3909896]}, "properties": {"man_made": "surveillance", "surveillance:type": "camera"}}, {"type": "Feature", "geometry": {"type": "Point", "coordinates": [-61.5954238, 16.2521959]}, "properties": {"camera:direction": "110", "camera:mount": "traffic_signals", "camera:type": "fixed", "contact:webcam": "trafikera.fr", "man_made": "surveillance", "operator:wikidata": "Q92940106", "surveillance": "outdoor", "surveillance:type": "camera", "surveillance:zone": "traffic"}}, {"type": "Feature", "geometry": {"type": "Point", "coordinates": [-61.5702892, 16.2631342]}, "properties": {"camera:direction": "27", "camera:type": "fixed", "contact:webcam": "trafikera.fr", "man_made": "surveillance", "operator": "Trafikera", "operator:wikipedia": "Q92940106", "surveillance": "outdoor", "surveillance:type": "camera", "surveillance:zone": "traffic"}}, {"type": "Feature", "geometry": {"type": "Point", "coordinates": [-61.5121692, 16.2700206]}, "properties": {"camera:direction": "18", "camera:type": "fixed", "contact:webcam": "trafikera.fr", "man_made": "surveillance", "operator:wikidata": "Q92940106", "surveillance": "outdoor", "surveillance:type": "camera", "surveillance:zone": "traffic"}}, {"type": "Feature", "geometry": {"type": "Point", "coordinates": [-61.5113003, 16.2585365]}, "properties": {"camera:direction": "17", "camera:mount": "traffic_signals", "camera:type": "fixed", "contact:webcam": "trafikera.fr", "man_made": "surveillance", "name": "Trafikera", "operator": "Trafikera", "operator:wikidata": "Q92940106", "surveillance": "outdoor", "surveillance:type": "camera", "surveillance:zone": "traffic"}}, {"type": "Feature", "geometry": {"type": "Point", "coordinates": [-61.5089412, 16.2601974]}, "properties": {"man_made": "surveillance", "surveillance:type": "camera"}}, {"type": "Feature", "geometry": {"type": "Point", "coordinates": [-61.5089646, 16.2601988]}, "properties": {"man_made": "surveillance", "surveillance:type": "camera"}}, {"type": "Feature", "geometry": {"type": "Point", "coordinates": [-61.5086317, 16.2603296]}, "properties": {"man_made": "surveillance", "surveillance:type": "camera"}}, {"type": "Feature", "geometry": {"type": "Point", "coordinates": [-61.5713527, 16.2476935]}, "properties": {"man_made": "surveillance"}}, {"type": "Feature", "geometry": {"type": "Point", "coordinates": [-61.3653502, 16.3331681]}, "properties": {"man_made": "surveillance"}}, {"type": "Feature", "geometry": {"type": "Point", "coordinates": [-61.5896835, 16.2492378]}, "properties": {"camera:mount": "pole", "contact:webcam": "trafikera.fr", "man_made": "surveillance", "operator:wikidata": "Q92940106", "surveillance": "traffic", "surveillance:type": "camera", "surveillance:zone": "traffic"}}, {"type": "Feature", "geometry": {"type": "Point", "coordinates": [-61.7684788, 16.0582117]}, "properties": {"camera:mount": "pole", "camera:type": "dome", "man_made": "surveillance", "surveillance": "public", "surveillance:type": "camera", "surveillance:zone": "town"}}, {"type": "Feature", "geometry": {"type": "Point", "coordinates": [-61.5114903, 16.264669]}, "properties": {"camera:mount": "pole", "camera:type": "dome", "man_made": "surveillance", "surveillance": "public", "surveillance:type": "camera", "surveillance:zone": "town"}}, {"type": "Feature", "geometry": {"type": "Point", "coordinates": [-61.5358799, 16.2369079]}, "properties": {"camera:mount": "pole", "camera:type": "fixed", "man_made": "surveillance", "surveillance": "public", "surveillance:type": "camera", "surveillance:zone": "town"}}, {"type": "Feature", "geometry": {"type": "Point", "coordinates": [-61.5339319, 16.2361061]}, "properties": {"camera:mount": "wall", "camera:type": "dome", "man_made": "surveillance", "surveillance": "outdoor", "surveillance:type": "camera", "surveillance:zone": "building"}}, {"type": "Feature", "geometry": {"type": "Point", "coordinates": [-61.5380832, 16.2413443]}, "properties": {"camera:mount": "pole", "camera:type": "fixed", "man_made": "surveillance", "surveillance": "public", "surveillance:type": "camera", "surveillance:zone": "town"}}, {"type": "Feature", "geometry": {"type": "Point", "coordinates": [-61.5380851, 16.2413516]}, "properties": {"camera:mount": "pole", "camera:type": "fixed", "man_made": "surveillance", "surveillance": "public", "surveillance:type": "camera", "surveillance:zone": "town"}}, {"type": "Feature", "geometry": {"type": "Point", "coordinates": [-61.5835599, 16.2650397]}, "properties": {"camera:mount": "pole", "camera:type": "dome", "man_made": "surveillance", "surveillance": "public", "surveillance:type": "camera", "surveillance:zone": "town"}}, {"type": "Feature", "geometry": {"type": "Point", "coordinates": [-61.5875, 16.2652156]}, "properties": {"camera:mount": "pole", "camera:type": "dome", "man_made": "surveillance", "surveillance": "public", "surveillance:type": "camera", "surveillance:zone": "town"}}, {"type": "Feature", "geometry": {"type": "Point", "coordinates": [-61.5873007, 16.26658]}, "properties": {"camera:mount": "pole", "camera:type": "dome", "man_made": "surveillance", "surveillance": "public", "surveillance:type": "camera", "surveillance:zone": "town"}}, {"type": "Feature", "geometry": {"type": "Point", "coordinates": [-61.5871493, 16.2682771]}, "properties": {"camera:mount": "pole", "camera:type": "fixed", "man_made": "surveillance", "surveillance": "public", "surveillance:type": "camera"}}, {"type": "Feature", "geometry": {"type": "Point", "coordinates": [-61.5874225, 16.2547484]}, "properties": {"camera:mount": "pole", "camera:type": "dome", "man_made": "surveillance", "surveillance": "public", "surveillance:type": "camera", "surveillance:zone": "town"}}, {"type": "Feature", "geometry": {"type": "Point", "coordinates": [-61.5896949, 16.2546966]}, "properties": {"camera:mount": "street_lamp", "camera:type": "dome", "highway": "street_lamp", "man_made": "surveillance", "surveillance": "public", "surveillance:type": "camera", "surveillance:zone": "town"}}, {"type": "Feature", "geometry": {"type": "Point", "coordinates": [-61.7284315, 15.9922717]}, "properties": {"camera:mount": "pole", "camera:type": "dome", "man_made": "surveillance", "surveillance": "outdoor", "surveillance:type": "camera", "surveillance:zone": "building"}}, {"type": "Feature", "geometry": {"type": "Point", "coordinates": [-61.7866475, 16.3213668]}, "properties": {"camera:mount": "pole", "camera:type": "dome", "man_made": "surveillance", "surveillance": "public", "surveillance:type": "camera", "surveillance:zone": "town"}}, {"type": "Feature", "geometry": {"type": "Point", "coordinates": [-61.7945013, 16.3044614]}, "properties": {"camera:mount": "pole", "camera:type": "dome", "man_made": "surveillance", "surveillance": "public", "surveillance:type": "camera", "surveillance:zone": "town"}}, {"type": "Feature", "geometry": {"type": "Point", "coordinates": [-61.7696822, 16.13131]}, "properties": {"camera:mount": "wall", "camera:type": "panning", "man_made": "surveillance", "surveillance": "outdoor", "surveillance:type": "camera", "surveillance:zone": "bank"}}, {"type": "Feature", "geometry": {"type": "Point", "coordinates": [-61.7697767, 16.1313746]}, "properties": {"camera:mount": "wall", "camera:type": "fixed", "man_made": "surveillance", "surveillance:type": "camera", "surveillance:zone": "bank"}}, {"type": "Feature", "geometry": {"type": "Point", "coordinates": [-61.6442994, 15.9681636]}, "properties": {"camera:mount": "pole", "camera:type": "dome", "man_made": "surveillance", "surveillance": "public", "surveillance:type": "camera", "surveillance:zone": "town"}}, {"type": "Feature", "geometry": {"type": "Point", "coordinates": [-61.5691195, 16.0524974]}, "properties": {"man_made": "surveillance"}}, {"type": "Feature", "geometry": {"type": "Point", "coordinates": [-61.4961443, 16.3782321]}, "properties": {"camera:mount": "street_lamp", "camera:type": "fixed", "highway": "street_lamp", "man_made": "surveillance", "surveillance:type": "camera", "surveillance:zone": "town"}}, {"type": "Feature", "geometry": {"type": "Point", "coordinates": [-61.342652, 16.3287123]}, "properties": {"camera:mount": "pole", "camera:type": "dome", "man_made": "surveillance", "surveillance": "public", "surveillance:type": "camera", "surveillance:zone": "town"}}, {"type": "Feature", "geometry": {"type": "Point", "coordinates": [-61.3497146, 16.3343176]}, "properties": {"camera:mount": "street_lamp", "camera:type": "dome", "highway": "street_lamp", "man_made": "surveillance", "surveillance": "public", "surveillance:type": "camera", "surveillance:zone": "town"}}, {"type": "Feature", "geometry": {"type": "Point", "coordinates": [-61.3466268, 16.3316945]}, "properties": {"man_made": "surveillance", "name": "Camera"}}, {"type": "Feature", "geometry": {"type": "Point", "coordinates": [-61.346301, 16.3313016]}, "properties": {"man_made": "surveillance", "name": "Camera"}}, {"type": "Feature", "geometry": {"type": "Point", "coordinates": [-61.5340595, 16.2311403]}, "properties": {"camera:mount": "ceiling", "camera:type": "dome", "man_made": "surveillance", "surveillance": "public", "surveillance:type": "camera", "surveillance:zone": "town"}}, {"type": "Feature", "geometry": {"type": "Point", "coordinates": [-61.4914051, 16.3062154]}, "properties": {"man_made": "surveillance"}}, {"type": "Feature", "geometry": {"type": "Point", "coordinates": [-61.5705482, 16.2535303]}, "properties": {"man_made": "surveillance"}}, {"type": "Feature", "geometry": {"type": "Point", "coordinates": [-61.5226721, 16.2390672]}, "properties": {"camera:direction": "340", "contact:webcam": "https://www.trafikera.fr/", "man_made": "surveillance", "operator:wikidata": "Q92940106", "surveillance": "traffic", "surveillance:type": "camera", "surveillance:zone": "traffic"}}, {"type": "Feature", "geometry": {"type": "Point", "coordinates": [-61.5352835, 16.2537196]}, "properties": {"camera:direction": "270", "contact:webcam": "https://www.trafikera.fr/", "man_made": "surveillance", "operator:wikidata": "Q92940106", "surveillance": "traffic", "surveillance:type": "camera", "surveillance:zone": "traffic"}}, {"type": "Feature", "geometry": {"type": "Point", "coordinates": [-61.5400645, 16.2539538]}, "properties": {"camera:direction": "250", "contact:webcam": "https://www.trafikera.fr/", "man_made": "surveillance", "name": "Trafikera", "operator:wikidata": "Q92940106", "surveillance": "traffic", "surveillance:type": "camera", "surveillance:zone": "traffic"}}, {"type": "Feature", "geometry": {"type": "Point", "coordinates": [-61.5421399, 16.2537567]}, "properties": {"contact:webcam": "https://www.trafikera.fr/", "man_made": "surveillance", "operator:wikidata": "Q92940106", "surveillance": "traffic", "surveillance:type": "camera", "surveillance:zone": "traffic"}}, {"type": "Feature", "geometry": {"type": "Point", "coordinates": [-61.4193703, 16.4069813]}, "properties": {"man_made": "surveillance"}}, {"type": "Feature", "geometry": {"type": "Point", "coordinates": [-61.5387943, 16.2380458]}, "properties": {"man_made": "surveillance"}}, {"type": "Feature", "geometry": {"type": "Point", "coordinates": [-61.537905, 16.2352428]}, "properties": {"man_made": "surveillance"}}, {"type": "Feature", "geometry": {"type": "Point", "coordinates": [-61.5376364, 16.2350093]}, "properties": {"man_made": "surveillance"}}, {"type": "Feature", "geometry": {"type": "Point", "coordinates": [-61.720126, 15.986951]}, "properties": {"camera:direction": "30", "camera:mount": "pole", "camera:type": "fixed", "contact:webcam": "https://www.trafikera.fr/indexm.php", "man_made": "surveillance", "surveillance": "traffic", "surveillance:type": "camera", "surveillance:zone": "traffic"}}, {"type": "Feature", "geometry": {"type": "Point", "coordinates": [-61.5926055, 16.2500656]}, "properties": {"man_made": "surveillance"}}, {"type": "Feature", "geometry": {"type": "Point", "coordinates": [-61.5585795, 16.2418497]}, "properties": {"man_made": "surveillance", "surveillance": "camera"}}, {"type": "Feature", "geometry": {"type": "Point", "coordinates": [-61.5581128, 16.2425647]}, "properties": {"man_made": "surveillance", "surveillance": "camera"}}, {"type": "Feature", "geometry": {"type": "Point", "coordinates": [-61.5547541, 16.2416003]}, "properties": {"man_made": "surveillance", "surveillance": "camera"}}, {"type": "Feature", "geometry": {"type": "Point", "coordinates": [-61.7632037, 16.0600059]}, "properties": {"camera:mount": "pole", "man_made": "surveillance", "surveillance": "public", "surveillance:type": "camera"}}, {"type": "Feature", "geometry": {"type": "Point", "coordinates": [-61.5579431, 16.2425548]}, "properties": {"man_made": "surveillance", "surveillance": "camera"}}, {"type": "Feature", "geometry": {"type": "Point", "coordinates": [-61.5588681, 16.2424633]}, "properties": {"man_made": "surveillance", "surveillance": "camera"}}, {"type": "Feature", "geometry": {"type": "Point", "coordinates": [-61.5583292, 16.2422756]}, "properties": {"man_made": "surveillance", "surveillance": "camera"}}, {"type": "Feature", "geometry": {"type": "Point", "coordinates": [-61.5546842, 16.2416094]}, "properties": {"man_made": "surveillance", "surveillance": "camera"}}, {"type": "Feature", "geometry": {"type": "Point", "coordinates": [-61.5159888, 16.2706816]}, "properties": {"man_made": "surveillance", "surveillance:type": "camera"}}, {"type": "Feature", "geometry": {"type": "Point", "coordinates": [-61.5166483, 16.2703355]}, "properties": {"man_made": "surveillance", "surveillance:type": "camera"}}], "networks": []}