{"type": "FeatureCollection", "features": [{"type": "Feature", "geometry": {"type": "Point", "coordinates": [-13.5747212, 9.6369413]}, "properties": {"id": 6072823214, "man_made": "surveillance", "name": "ALMATA S\u00e9curit\u00e9", "phone": "+224623435195", "service": "Gardiennage, Protection rapproch\u00e9e, nettoyage,", "data_source": "planet_osm"}}, {"type": "Feature", "geometry": {"type": "Point", "coordinates": [-12.0362838, 8.9022308]}, "properties": {"id": 7861420485, "man_made": "surveillance", "data_source": "planet_osm"}}], "networks": []}